pyaxm/__init__.py
pyaxm/abm_requests.py
pyaxm/cli.py
pyaxm/client.py
pyaxm/models.py
pyaxm/utils.py
pyaxm-2026.1.23.dist-info/METADATA
pyaxm-2026.1.23.dist-info/WHEEL
pyaxm-2026.1.23.dist-info/entry_points.txt
pyaxm-2026.1.23.dist-info/licenses/LICENSE
pyaxm-2026.1.23.dist-info/RECORD
