Metadata-Version: 2.4
Name: pyaxm
Version: 2026.1.23
Summary: Query Apple Business Manager using Python
Project-URL: Repository, https://github.com/kaincenteno/pyaxm
License-Expression: GPL-3.0-or-later
License-File: LICENSE
Keywords: abm,apple business manager,axm
Requires-Python: >=3.10
Requires-Dist: authlib
Requires-Dist: pandas
Requires-Dist: pycryptodomex
Requires-Dist: pydantic
Requires-Dist: requests
Requires-Dist: typer
